jo3util/__init__.py
jo3util/debug.py
jo3util/eqx.py
jo3util/fn.py
jo3util/hollow.py
jo3util/memory.py
jo3util/root.py
jo3util/store.py
jo3util/string.py
jo3util/time_out.py
jo3util/timing.py
jo3util/vis.py
jo3util/warning.py
jo3util-0.0.21.dist-info/LICENSE
jo3util-0.0.21.dist-info/METADATA
jo3util-0.0.21.dist-info/WHEEL
jo3util-0.0.21.dist-info/top_level.txt
jo3util-0.0.21.dist-info/RECORD
