Metadata-Version: 2.2
Name: jo3util
Version: 0.0.21
Author-email: Jochem Hölscher <a.fake@e.mail>
Project-URL: homepage, https://github.com/JJJHolscher/jo3util
Classifier: Programming Language :: Python :: 3
Classifier: License :: OSI Approved :: MIT License
Classifier: Operating System :: OS Independent
Requires-Python: >=3.11
License-File: LICENSE
